<?xml version="1.0" encoding="UTF-8"?>
<iati-organisations generated-datetime="2016-02-15T15:35:12+00:00" version="2.01">
  <!-- Generated By AidStream -->
  <iati-organisation default-currency="GBP" last-updated-datetime="2016-02-15T03:34:56+00:00" xml:lang="en">
    <organisation-identifier>GB-CHC-328206</organisation-identifier>
    <name>
      <narrative>Womankind Worldwide</narrative>
    </name>
    <reporting-org ref="GB-CHC-328206" type="21">
      <narrative xml:lang="en">Womankind Worldwide</narrative>
    </reporting-org>
    <document-link format="application/pdf" url="http://www.womankind.org.uk/wp-content/uploads/2014/03/Womankind-Worldwide-strategy-2013-2018.pdf">
      <title>
        <narrative>Innovation and Evidence: A Global Transformation Strategy to 2018</narrative>
      </title>
      <category code="B02"/>
      <language code="en"/>
    </document-link>
    <document-link format="application/pdf" url="http://www.womankind.org.uk/about/impact-report/">
      <title>
        <narrative>Womankind Impact Report 2013-2014 - Transforming the Lives of Women and Girls </narrative>
      </title>
      <category code="B01"/>
      <language code="en"/>
    </document-link>
    <document-link format="application/pdf" url="http://www.womankind.org.uk/about/impact-report/">
      <title>
        <narrative>Womankind Impact Report 2013-2014 - Transforming the Lives of Women and Girls </narrative>
      </title>
      <category code="B01"/>
      <language code="en"/>
    </document-link>
    <document-link format="application/pdf" url="http://www.womankind.org.uk/about/our-finances/">
      <title>
        <narrative>Report and Financial Statements for the Year Ended 31 March 2014 </narrative>
      </title>
      <category code="B06"/>
      <language code="en"/>
    </document-link>
    <document-link format="application/pdf" url="http://www.womankind.org.uk/about/impact-report/">
      <title>
        <narrative>Womankind Impact Report 2013-2014 - Transforming the Lives of Women and Girls </narrative>
      </title>
      <category code="B01"/>
      <language code="en"/>
    </document-link>
    <document-link format="application/pdf" url="http://www.womankind.org.uk/about/our-finances/">
      <title>
        <narrative>Report and Financial Statements for the Year Ended 31 March 2014 </narrative>
      </title>
      <category code="B06"/>
      <language code="en"/>
    </document-link>
    <document-link format="application/pdf" url="https://www.womankind.org.uk/docs/default-source/Annual-Reports/impact-report-2014-15-final-digital-compressed.pdf?sfvrsn=0">
      <title>
        <narrative>Womankind Worldwide Impact Report 2014-15</narrative>
      </title>
      <category code="B01"/>
      <language code="en"/>
    </document-link>
    <document-link format="application/pdf" url="https://www.womankind.org.uk/about-us/finances">
      <title>
        <narrative>Womankind financial report 2014-15</narrative>
      </title>
      <category code="B06"/>
    </document-link>
  </iati-organisation>
</iati-organisations>
